sem3/dsd/lab_1/q2.v
module q2(A,B,C,D,f);
input A,B,C,D;
output f;
assign f=(B&~C)|(C&~D);
endmodule

sem3/dsd/lab_1/q2_tb.v
`timescale 1ns/1ns
`include "q2.v"
module q2_tb;
reg A,B,C,D;
wire f;
q2 uut(A,B,C,D,f);
initial
begin
$dumpfile("q2_tb.vcd");
$dumpvars(0,q2_tb);
A=0;B=0;C=0;D=0;#20;
A=0;B=0;C=0;D=1;#20;
A=0;B=0;C=1;D=0;#20;
A=0;B=0;C=1;D=1;#20;
A=0;B=1;C=0;D=0;#20;
A=0;B=1;C=0;D=1;#20;
A=0;B=1;C=1;D=0;#20;
A=0;B=1;C=1;D=1;#20;
A=1;B=0;C=0;D=0;#20;
A=1;B=0;C=0;D=1;#20;
A=1;B=0;C=1;D=0;#20;
A=1;B=0;C=1;D=1;#20;
A=1;B=1;C=0;D=0;#20;
A=1;B=1;C=0;D=1;#20;
A=1;B=1;C=1;D=0;#20;
A=1;B=1;C=1;D=1;#20;
$display("test complete");
end
endmodule

sem3/dsd/lab_1/q2_tb.vcd
$date
	Tue Aug  8 16:02:00 2023
$end
$version
	Icarus Verilog
$end
$timescale
	1ns
$end
$scope module q2_tb $end
$var wire 1 ! f $end
$var reg 1 " A $end
$var reg 1 # B $end
$var reg 1 $ C $end
$var reg 1 % D $end
$scope module uut $end
$var wire 1 " A $end
$var wire 1 # B $end
$var wire 1 $ C $end
$var wire 1 % D $end
$var wire 1 ! f $end
$upscope $end
$upscope $end
$enddefinitions $end
#0
$dumpvars
0%
0$
0#
0"
0!
$end
#20
1%
#40
1!
0%
1$
#60
0!
1%
#80
1!
0%
0$
1#
#100
1%
#120
0%
1$
#140
0!
1%
#160
0%
0$
0#
1"
#180
1%
#200
1!
0%
1$
#220
0!
1%
#240
1!
0%
0$
1#
#260
1%
#280
0%
1$
#300
0!
1%
