sem3/dsd/lab_1/q3.v
module q3(A,B,C,D,f);
input A,B,C,D;
output f;
assign f=~((C|D)&(B|C)&(~A|~B|~C|~D));
endmodule

sem3/dsd/lab_1/q3_tb.v
`timescale 1ns/1ns
`include "q3.v"
module q3_tb;
reg A,B,C,D;
wire f;
q3 uut(A,B,C,D,f);
initial
begin
$dumpfile("q3_tb.vcd");
$dumpvars(0,q3_tb);
A=0;B=0;C=0;D=0;#20;
A=0;B=0;C=0;D=1;#20;
A=0;B=0;C=1;D=0;#20;
A=0;B=0;C=1;D=1;#20;
A=0;B=1;C=0;D=0;#20;
A=0;B=1;C=0;D=1;#20;
A=0;B=1;C=1;D=0;#20;
A=0;B=1;C=1;D=1;#20;
A=1;B=0;C=0;D=0;#20;
A=1;B=0;C=0;D=1;#20;
A=1;B=0;C=1;D=0;#20;
A=1;B=0;C=1;D=1;#20;
A=1;B=1;C=0;D=0;#20;
A=1;B=1;C=0;D=1;#20;
A=1;B=1;C=1;D=0;#20;
A=1;B=1;C=1;D=1;#20;
$display("test complete");
end
endmodule

sem3/dsd/lab_1/q3_tb.vcd
$date
	Tue Aug  8 15:25:40 2023
$end
$version
	Icarus Verilog
$end
$timescale
	1ns
$end
$scope module q3_tb $end
$var wire 1 ! f $end
$var reg 1 " A $end
$var reg 1 # B $end
$var reg 1 $ C $end
$var reg 1 % D $end
$scope module uut $end
$var wire 1 " A $end
$var wire 1 # B $end
$var wire 1 $ C $end
$var wire 1 % D $end
$var wire 1 ! f $end
$upscope $end
$upscope $end
$enddefinitions $end
#0
$dumpvars
0%
0$
0#
0"
1!
$end
#20
1%
#40
0!
0%
1$
#60
1%
#80
1!
0%
0$
1#
#100
0!
1%
#120
0%
1$
#140
1%
#160
1!
0%
0$
0#
1"
#180
1%
#200
0!
0%
1$
#220
1%
#240
1!
0%
0$
1#
#260
0!
1%
#280
0%
1$
#300
1!
1%
