sem3/dsd/lab_2/q1.v
module q1(a,b,c,d,f);
input a,b,c,d;
output f;
assign g=(~c&d)|(c&~d);
assign f=(g&a)|(b&~g);
endmodule

sem3/dsd/lab_2/q1_tb.v
`timescale 1ns/1ns
`include "q1.v"
module q1_tb;
reg a,b,c,d;
wire f;
q1 uut(a,b,c,d,f);
initial
begin
$dumpfile("q1_tb.vcd");
$dumpvars(0,q1_tb);
a=0;b=0;c=0;d=0;#20;
a=0;b=0;c=0;d=1;#20;
a=0;b=0;c=1;d=0;#20;
a=0;b=0;c=1;d=1;#20;
a=0;b=1;c=0;d=0;#20;
a=0;b=1;c=0;d=1;#20;
a=0;b=1;c=1;d=0;#20;
a=0;b=1;c=1;d=1;#20;
a=1;b=0;c=0;d=0;#20;
a=1;b=0;c=0;d=1;#20;
a=1;b=0;c=1;d=0;#20;
a=1;b=0;c=1;d=1;#20;
a=1;b=1;c=0;d=0;#20;
a=1;b=1;c=0;d=1;#20;
a=1;b=1;c=1;d=0;#20;
a=1;b=1;c=1;d=1;#20;
$display("test complete");
end
endmodule

sem3/dsd/lab_2/q1_tb.vcd
$date
	Tue Aug 22 14:09:25 2023
$end
$version
	Icarus Verilog
$end
$timescale
	1ns
$end
$scope module q1_tb $end
$var wire 1 ! f $end
$var reg 1 " a $end
$var reg 1 # b $end
$var reg 1 $ c $end
$var reg 1 % d $end
$scope module uut $end
$var wire 1 " a $end
$var wire 1 # b $end
$var wire 1 $ c $end
$var wire 1 % d $end
$var wire 1 ! f $end
$var wire 1 & g $end
$upscope $end
$upscope $end
$enddefinitions $end
#0
$dumpvars
0&
0%
0$
0#
0"
0!
$end
#20
1&
1%
#40
0%
1$
#60
0&
1%
#80
1!
0%
0$
1#
#100
0!
1&
1%
#120
0%
1$
#140
1!
0&
1%
#160
0!
0%
0$
0#
1"
#180
1!
1&
1%
#200
0%
1$
#220
0!
0&
1%
#240
1!
0%
0$
1#
#260
1&
1%
#280
0%
1$
#300
0&
1%
