sem3/dsd/lab_2/q2.v
module q2(a,b,cin,s,cout);
input a,b,cin;
output s,cout;
assign s=(a^b)^cin;
assign cout=(a&b)|(b&cin)|(a&cin);
endmodule

sem3/dsd/lab_2/q2_tb.v
`timescale 1ns/1ns
`include "q2.v"
module q2_tb;
reg a,b,cin;
wire s,cout;
q2 uut(a,b,cin,s,cout);
initial
begin
$dumpfile("q2_tb.vcd");
$dumpvars(0,q2_tb);
a=0;b=0;cin=0;#20;
a=0;b=0;cin=1;#20;
a=0;b=1;cin=0;#20;
a=0;b=1;cin=1;#20;
a=1;b=0;cin=0;#20;
a=1;b=0;cin=1;#20;
a=1;b=1;cin=0;#20;
a=1;b=1;cin=1;#20;
$display("test cinomplete");
end
endmodule

sem3/dsd/lab_2/q2_tb.vcd
$date
	Tue Aug 22 14:19:05 2023
$end
$version
	Icarus Verilog
$end
$timescale
	1ns
$end
$scope module q2_tb $end
$var wire 1 ! s $end
$var wire 1 " cout $end
$var reg 1 # a $end
$var reg 1 $ b $end
$var reg 1 % cin $end
$scope module uut $end
$var wire 1 # a $end
$var wire 1 $ b $end
$var wire 1 % cin $end
$var wire 1 " cout $end
$var wire 1 ! s $end
$upscope $end
$upscope $end
$enddefinitions $end
#0
$dumpvars
0%
0$
0#
0"
0!
$end
#20
1!
1%
#40
0%
1$
#60
1"
0!
1%
#80
0"
1!
0%
0$
1#
#100
1"
0!
1%
#120
0%
1$
#140
1!
1%
