sem3/dsd/lab_3/mux16.v
module mux16(a,s,f);
input [15:0]a;
input [3:0]s;
output f;
wire g,h;
mux8to1 m1(a[7:0],s[2:0],g);
mux8to1 m2(a[15:8],s[2:0],h);
mux2to1 m3(g,h,s[3],f);
endmodule

module mux8to1(w,s,f);
input [7:0]w;
input [2:0]s;
output reg f;
always@(w,s)
begin
	case (s)
		0:f=w[0];
		1:f=w[1];
		2:f=w[2];
		3:f=w[3];
		4:f=w[4];
		5:f=w[5];
		6:f=w[6];
		7:f=w[7];
	endcase
end 
endmodule
		
module mux2to1 (w0, w1, s, f1);
input w0, w1, s;
output f1;

assign f1 = s ? w1 : w0;
endmodule

sem3/dsd/lab_3/mux16_tb.v
`timescale 1ns/1ns
`include "mux16.v"
module mux16_tb;
reg [15:0]a;
reg [3:0]s;
wire f;

mux16 uut(a,s,f);
initial
begin
$dumpfile("mux16_tb.vcd");
$dumpvars(0,mux16_tb);
a=16'b1010101011110011;s=4'b0000;#20;
s=4'b0001;#20;
s=4'b0010;#20;
s=4'b0011;#20;
s=4'b0100;#20;
s=4'b0101;#20;
s=4'b0110;#20;
s=4'b0111;#20;
s=4'b1000;#20;
s=4'b1001;#20;
s=4'b1010;#20;
s=4'b1011;#20;
s=4'b1100;#20;
s=4'b1101;#20;
s=4'b1110;#20;
s=4'b1111;#20;
$display("test cinomplete");
end
endmodule

sem3/dsd/lab_3/mux16_tb.vcd
$date
	Tue Aug 29 15:28:32 2023
$end
$version
	Icarus Verilog
$end
$timescale
	1ns
$end
$scope module mux16_tb $end
$var wire 1 ! f $end
$var reg 16 " a [15:0] $end
$var reg 4 # s [3:0] $end
$scope module uut $end
$var wire 16 $ a [15:0] $end
$var wire 4 % s [3:0] $end
$var wire 1 & h $end
$var wire 1 ' g $end
$var wire 1 ! f $end
$scope module m1 $end
$var wire 3 ( s [2:0] $end
$var wire 8 ) w [7:0] $end
$var reg 1 ' f $end
$upscope $end
$scope module m2 $end
$var wire 3 * s [2:0] $end
$var wire 8 + w [7:0] $end
$var reg 1 & f $end
$upscope $end
$scope module m3 $end
$var wire 1 , s $end
$var wire 1 ' w0 $end
$var wire 1 & w1 $end
$var wire 1 ! f1 $end
$upscope $end
$upscope $end
$upscope $end
$enddefinitions $end
#0
$dumpvars
0,
b10101010 +
b0 *
b11110011 )
b0 (
1'
0&
b0 %
b1010101011110011 $
b0 #
b1010101011110011 "
1!
$end
#20
1&
b1 (
b1 *
b1 #
b1 %
#40
0!
0'
0&
b10 (
b10 *
b10 #
b10 %
#60
1&
b11 (
b11 *
b11 #
b11 %
#80
1!
1'
0&
b100 (
b100 *
b100 #
b100 %
#100
1&
b101 (
b101 *
b101 #
b101 %
#120
0&
b110 (
b110 *
b110 #
b110 %
#140
1&
b111 (
b111 *
b111 #
b111 %
#160
0!
0&
b0 (
b0 *
1,
b1000 #
b1000 %
#180
1!
1&
b1 (
b1 *
b1001 #
b1001 %
#200
0!
0'
0&
b10 (
b10 *
b1010 #
b1010 %
#220
1!
1&
b11 (
b11 *
b1011 #
b1011 %
#240
0!
1'
0&
b100 (
b100 *
b1100 #
b1100 %
#260
1!
1&
b101 (
b101 *
b1101 #
b1101 %
#280
0!
0&
b110 (
b110 *
b1110 #
b1110 %
#300
1!
1&
b111 (
b111 *
b1111 #
b1111 %
