sem3/dsd/lab_4/pe16_4.v
module pe16_4(en,i,y,z);
  input en;
  input [15:0]i;
  integer k;
  output reg z;
  output reg [3:0]y;
  always @(en,i)
  begin
    if(en==1)
      begin
      z=1;
      if (i==0) z=0;
      for(k=15;k>=0;k=k-1)
         if (i[k]==1) y=k;
      end
    else begin y=4'bzzzz;z=0; end 
  end
endmodule

sem3/dsd/lab_4/pe16_4_tb.v
`timescale 1ns/1ns
`include "pe16_4.v"
module pe16_4_tb;
  reg [15:0]i;
  reg en;
  wire [3:0]y;
  wire z;

  pe16_4 uut(en,i,y,z);
  initial
    begin
      $dumpfile("pe16_4_tb.vcd");
      $dumpvars(0,pe16_4_tb);
            en=0;i=16'bx;#20;
      	    en=1;
      	    i=32768;#20;
      	    i=16384;#20;
      	    i=8192;#20;
      	    i=4096;#20;
      	    i=2048;#20
      	    i=1024;#20;
      	    i=512;#20;
      	    i=256;#20;
      	    i=128;#20;
      	    i=64;#20;
            i=32;#20;
            i=16;#20;
            i=8;#20;
            i=4;#20;
            i=2;#20;
            i=0;#20;
      $display("test complete");
    end
endmodule

sem3/dsd/lab_4/pe16_4_tb.vcd
$date
	Tue Sep  5 15:55:08 2023
$end
$version
	Icarus Verilog
$end
$timescale
	1ns
$end
$scope module pe16_4_tb $end
$var wire 1 ! z $end
$var wire 4 " y [3:0] $end
$var reg 1 # en $end
$var reg 16 $ i [15:0] $end
$scope module uut $end
$var wire 1 # en $end
$var wire 16 % i [15:0] $end
$var reg 4 & y [3:0] $end
$var reg 1 ! z $end
$var integer 32 ' k [31:0] $end
$upscope $end
$upscope $end
$enddefinitions $end
#0
$dumpvars
bx '
bz &
bx %
bx $
0#
bz "
0!
$end
#20
b1111 "
b1111 &
b11111111111111111111111111111111 '
1!
b1000000000000000 $
b1000000000000000 %
1#
#40
b1110 "
b1110 &
b11111111111111111111111111111111 '
b100000000000000 $
b100000000000000 %
#60
b1101 "
b1101 &
b11111111111111111111111111111111 '
b10000000000000 $
b10000000000000 %
#80
b1100 "
b1100 &
b11111111111111111111111111111111 '
b1000000000000 $
b1000000000000 %
#100
b1011 "
b1011 &
b11111111111111111111111111111111 '
b100000000000 $
b100000000000 %
#120
b1010 "
b1010 &
b11111111111111111111111111111111 '
b10000000000 $
b10000000000 %
#140
b1001 "
b1001 &
b11111111111111111111111111111111 '
b1000000000 $
b1000000000 %
#160
b1000 "
b1000 &
b11111111111111111111111111111111 '
b100000000 $
b100000000 %
#180
b111 "
b111 &
b11111111111111111111111111111111 '
b10000000 $
b10000000 %
#200
b110 "
b110 &
b11111111111111111111111111111111 '
b1000000 $
b1000000 %
#220
b101 "
b101 &
b11111111111111111111111111111111 '
b100000 $
b100000 %
#240
b100 "
b100 &
b11111111111111111111111111111111 '
b10000 $
b10000 %
#260
b11 "
b11 &
b11111111111111111111111111111111 '
b1000 $
b1000 %
#280
b10 "
b10 &
b11111111111111111111111111111111 '
b100 $
b100 %
#300
b1 "
b1 &
b11111111111111111111111111111111 '
b10 $
b10 %
#320
b11111111111111111111111111111111 '
0!
b0 $
b0 %
