sem3/dsd/lab_4/pe.v
module pe(s,f,en,z);
 	input [3:0]s; input en;
 	output reg [1:0]f; output reg z;
always @ (s,en) 
begin
z=1;
    if(en==1) begin
    casex(s)
        4'b1XXX: f = 2'b11; 
        4'b01XX: f = 2'b10; 
        4'b001X: f = 2'b01; 
        4'b0001: f = 2'b00;
        4'b0000:z=0;
    endcase
    end
end

endmodule

sem3/dsd/lab_4/pe_tb.v
`timescale 1ns/1ns
`include "pe.v"
module pe_tb;
    wire [1:0] f;
    wire z;
    reg[3:0] s;
    reg en;
    pe uut (s,f,en,z); integer i;
    initial begin
        $dumpfile("pe_tb.vcd");
        $dumpvars(0,pe_tb);
        en=1;
        for(i=0;i<16;i=i+1) begin
        
            s = i;#20; end
        $display("test complete");
    end
endmodule

sem3/dsd/lab_4/pe_tb.vcd
$date
	Tue Sep  5 15:49:38 2023
$end
$version
	Icarus Verilog
$end
$timescale
	1ns
$end
$scope module pe_tb $end
$var wire 1 ! z $end
$var wire 2 " f [1:0] $end
$var reg 1 # en $end
$var reg 4 $ s [3:0] $end
$var integer 32 % i [31:0] $end
$scope module uut $end
$var wire 1 # en $end
$var wire 4 & s [3:0] $end
$var reg 2 ' f [1:0] $end
$var reg 1 ! z $end
$upscope $end
$upscope $end
$enddefinitions $end
#0
$dumpvars
bx '
b0 &
b0 %
b0 $
1#
bx "
0!
$end
#20
b0 "
b0 '
1!
b1 $
b1 &
b1 %
#40
b1 "
b1 '
b10 $
b10 &
b10 %
#60
b11 $
b11 &
b11 %
#80
b10 "
b10 '
b100 $
b100 &
b100 %
#100
b101 $
b101 &
b101 %
#120
b110 $
b110 &
b110 %
#140
b111 $
b111 &
b111 %
#160
b11 "
b11 '
b1000 $
b1000 &
b1000 %
#180
b1001 $
b1001 &
b1001 %
#200
b1010 $
b1010 &
b1010 %
#220
b1011 $
b1011 &
b1011 %
#240
b1100 $
b1100 &
b1100 %
#260
b1101 $
b1101 &
b1101 %
#280
b1110 $
b1110 &
b1110 %
#300
b1111 $
b1111 &
b1111 %
#320
b10000 %
