sem3/dsd/lab_5/q1.v
module q1(A,B,C,D,f);
	input A,B,C,D;
	wire f1;output f;
	     mux4_1 m1((!A|B),~B,(!A|B),1'b0,C,D,f1);
	assign f=f1;
endmodule

module mux4_1(w0,w1,w2,w3,s1,s0,f);
	input w0,w1,w2,w3,s1,s0;
	output reg f;
	always @(s1,s0)
	begin
		if (s1==1'b0)
		begin
			if (s0==1'b0) f=w0;
			else f=w1;
		end
		else 
		begin
		    if(s0==1'b0) f=w2;
		    else f=w3;
		end
	end
endmodule

sem3/dsd/lab_5/q1_tb.v
`timescale 1ns/1ns
`include "q1.v"

module q1_tb;
  reg A, B, C, D;
  wire f;

  q1 uut(A, B, C, D, f);

  integer i, j, k, l;

  initial begin
    $dumpfile("q1_tb.vcd");
    $dumpvars(0, q1_tb);
    for (i = 0; i <= 1; i = i + 1) begin
      for (j = 0; j <= 1; j = j + 1) begin
        for (k = 0; k <= 1; k = k + 1) begin
          for (l = 0; l <= 1; l = l + 1) begin
            A = i;
            B = j;
            C = k;
            D = l;
            #10;
          end
        end
      end
    end
    $display("test complete");
    
  end
endmodule

sem3/dsd/lab_5/q1_tb.vcd
$date
	Tue Sep 26 20:28:28 2023
$end
$version
	Icarus Verilog
$end
$timescale
	1ns
$end
$scope module q1_tb $end
$var wire 1 ! f $end
$var reg 1 " A $end
$var reg 1 # B $end
$var reg 1 $ C $end
$var reg 1 % D $end
$var integer 32 & i [31:0] $end
$var integer 32 ' j [31:0] $end
$var integer 32 ( k [31:0] $end
$var integer 32 ) l [31:0] $end
$scope module uut $end
$var wire 1 " A $end
$var wire 1 # B $end
$var wire 1 $ C $end
$var wire 1 % D $end
$var wire 1 ! f $end
$var wire 1 * f1 $end
$scope module m1 $end
$var wire 1 % s0 $end
$var wire 1 $ s1 $end
$var wire 1 + w0 $end
$var wire 1 , w1 $end
$var wire 1 - w2 $end
$var wire 1 . w3 $end
$var reg 1 * f $end
$upscope $end
$upscope $end
$upscope $end
$enddefinitions $end
$comment Show the parameter values. $end
$dumpall
$end
#0
$dumpvars
0.
1-
1,
1+
1*
b0 )
b0 (
b0 '
b0 &
0%
0$
0#
0"
1!
$end
#10
1%
b1 )
#20
0%
1$
b1 (
b0 )
#30
0!
0*
1%
b1 )
#40
1!
1*
0,
0%
0$
1#
b1 '
b0 (
b0 )
#50
0!
0*
1%
b1 )
#60
1!
1*
0%
1$
b1 (
b0 )
#70
0!
0*
1%
b1 )
#80
1,
0+
0-
0%
0$
0#
1"
b1 &
b0 '
b0 (
b0 )
#90
1!
1*
1%
b1 )
#100
0!
0*
0%
1$
b1 (
b0 )
#110
1%
b1 )
#120
1!
1*
1+
0,
1-
0%
0$
1#
b1 '
b0 (
b0 )
#130
0!
0*
1%
b1 )
#140
1!
1*
0%
1$
b1 (
b0 )
#150
0!
0*
1%
b1 )
#160
b10 &
b10 '
b10 (
b10 )
