sem3/dsd/lab_4/decode24.v
module decode24(en,a,y);
	input en;
	input [1:0]a;
	output reg [3:0]y;
    always @ (a or en)
    begin
        if (en)
        begin
            if (a == 0) begin
                y[0] = 1;
                y[1] = 0;
                y[2] = 0;
                y[3] = 0;
            end
            else if (a == 1) begin
                y[0] = 0;
                y[1] = 1;
                y[2] = 0;
                y[3] = 0;
            end
            else if (a == 2) begin
                y[0] = 0;
                y[1] = 0;
                y[2] = 1;
                y[3] = 0;
            end
            else if (a == 3) begin
                y[0] = 0;
                y[1] = 0;
                y[2] = 0;
                y[3] = 1;
            end
        end
        else begin
            y[0] = 0;
            y[1] = 0;
            y[2] = 0;
            y[3] = 0;
        end
    end

endmodule

sem3/dsd/lab_5/q4.v
`include "../lab_4/decode24.v"
module q4(a,f);
	input [2:0]a;
	output f;
	wire [7:0]y;
	decode24 m1(~a[2],a[1:0],y[3:0]);
	decode24 m2(a[2],a[1:0],y[7:4]);
	assign f=y[3]|y[5]|y[6]|y[7];
endmodule

sem3/dsd/lab_5/q4_tb.v
`timescale 1ns/1ns
`include "q4.v"
module q4_tb;
    reg [2:0] a;
    wire f;
    q4 uut (a,f);
    integer i;
    initial begin
        $dumpfile("q4.vcd");
        $dumpvars(0,q4_tb);
        for(i=0;i<8;i=i+1) begin
           a=i;#10; end
        $display("test complete");
    end
endmodule

sem3/dsd/lab_5/q4.vcd
$date
	Tue Sep 12 09:36:21 2023
$end
$version
	Icarus Verilog
$end
$timescale
	1ns
$end
$scope module q4_tb $end
$var wire 1 ! f $end
$var reg 3 " a [2:0] $end
$var integer 32 # i [31:0] $end
$scope module uut $end
$var wire 3 $ a [2:0] $end
$var wire 1 ! f $end
$var wire 8 % y [7:0] $end
$scope module m1 $end
$var wire 2 & a [1:0] $end
$var wire 1 ' en $end
$var reg 4 ( y [3:0] $end
$upscope $end
$scope module m2 $end
$var wire 2 ) a [1:0] $end
$var wire 1 * en $end
$var reg 4 + y [3:0] $end
$upscope $end
$upscope $end
$upscope $end
$enddefinitions $end
$comment Show the parameter values. $end
$dumpall
$end
#0
$dumpvars
b0 +
0*
b0 )
b1 (
1'
b0 &
b1 %
b0 $
b0 #
b0 "
0!
$end
#10
b10 %
b10 (
b1 &
b1 )
b1 "
b1 $
b1 #
#20
b100 %
b100 (
b10 &
b10 )
b10 "
b10 $
b10 #
#30
1!
b1000 %
b1000 (
b11 &
b11 )
b11 "
b11 $
b11 #
#40
0!
0'
b0 (
b10000 %
b1 +
b0 &
1*
b0 )
b100 "
b100 $
b100 #
#50
1!
b100000 %
b10 +
b1 &
b1 )
b101 "
b101 $
b101 #
#60
b1000000 %
b100 +
b10 &
b10 )
b110 "
b110 $
b110 #
#70
b10000000 %
b1000 +
b11 &
b11 )
b111 "
b111 $
b111 #
#80
b1000 #
